bell/avr/mqtt/__init__.py
bell/avr/mqtt/client.py
bell/avr/mqtt/payloads.py
bell/avr/serial/__init__.py
bell/avr/serial/client.py
bell/avr/serial/pcc.py
bell/avr/serial/ports.py
bell/avr/utils/__init__.py
bell/avr/utils/decorators.py
bell/avr/utils/timing.py
bell_avr_libraries-0.1.11.dist-info/LICENSE
bell_avr_libraries-0.1.11.dist-info/WHEEL
bell_avr_libraries-0.1.11.dist-info/METADATA
bell_avr_libraries-0.1.11.dist-info/RECORD
