Metadata-Version: 2.1
Name: bell-avr-libraries
Version: 0.1.11
Summary: Common Python libraries used by parts of Bell AVR
Home-page: https://github.com/bellflight/AVR-Python-Libraries
License: MIT
Author: Chris Padilla
Author-email: cpadilla@bellflight.com
Requires-Python: >=3.8,<3.12
Classifier: License :: OSI Approved :: MIT License
Classifier: Programming Language :: Python :: 3
Classifier: Programming Language :: Python :: 3.8
Classifier: Programming Language :: Python :: 3.9
Classifier: Programming Language :: Python :: 3.10
Classifier: Programming Language :: Python :: 3.11
Provides-Extra: mqtt
Provides-Extra: serial
Requires-Dist: loguru (>=0.6.0,<0.7.0)
Requires-Dist: paho-mqtt (>=1.6.1,<2.0.0); extra == "mqtt"
Requires-Dist: pyserial (>=3.5,<4.0); extra == "serial"
